README.md
setup.cfg
setup.py
django_wallet.egg-info/PKG-INFO
django_wallet.egg-info/SOURCES.txt
django_wallet.egg-info/dependency_links.txt
django_wallet.egg-info/requires.txt
django_wallet.egg-info/top_level.txt
wallets/__init__.py
wallets/admin.py
wallets/apps.py
wallets/lib.py
wallets/models.py
wallets/signals.py
wallets/tasks.py
wallets/urls.py
wallets/views.py