Metadata-Version: 2.1
Name: django-wallet
Version: 0.3
Summary: Apple Wallet integration for a django project
Home-page: https://github.com/Silver3310/django-wallets
Author: Elivanov Alexey
Author-email: epifanov998@mail.ru
License: MIT
Download-URL: https://github.com/Silver3310/django-wallets/archive/v_02.tar.gz
Keywords: django,wallet,apple,pass
Platform: UNKNOWN
Classifier: Development Status :: 3 - Alpha
Classifier: Intended Audience :: Developers
Classifier: Topic :: Software Development :: Build Tools
Classifier: License :: OSI Approved :: MIT License
Classifier: Programming Language :: Python :: 3
Classifier: Programming Language :: Python :: 3.7
Classifier: Programming Language :: Python :: 3.8
